dbcw/__init__.py
dbcw/db_queries.json
dbcw/dbcw.py
dbcw-0.2.3.data/scripts/dbcw.py
dbcw-0.2.3.dist-info/LICENSE.md
dbcw-0.2.3.dist-info/METADATA
dbcw-0.2.3.dist-info/WHEEL
dbcw-0.2.3.dist-info/top_level.txt
dbcw-0.2.3.dist-info/RECORD
