Metadata-Version: 2.1
Name: dbcw
Version: 0.2.3
Summary: Database connection wrapper
Home-page: https://github.com/Stefanitsky/dbcw
Author: stefanitsky
Author-email: stefanitsky.mozdor@google.com
License: UNKNOWN
Project-URL: Documentation, https://github.com/Stefanitsky/dbcw/wiki
Project-URL: Say Thanks!, https://saythanks.io/to/Stefanitsky
Project-URL: Source, https://github.com/Stefanitsky/dbcw
Project-URL: Tracker, https://github.com/Stefanitsky/dbcw/issues
Keywords: db database tool wrapper connection connect
Platform: UNKNOWN
Classifier: Development Status :: 3 - Alpha
Classifier: Programming Language :: Python :: 3
Classifier: Programming Language :: Python :: 3.3
Classifier: Programming Language :: Python :: 3.4
Classifier: Programming Language :: Python :: 3.5
Classifier: Programming Language :: Python :: 3.6
Classifier: Programming Language :: Python :: 3.7
Classifier: License :: OSI Approved :: MIT License
Classifier: Operating System :: OS Independent
Classifier: Intended Audience :: Developers
Classifier: Topic :: Database :: Front-Ends
Requires-Dist: psycopg2
Requires-Dist: mysql-connector
